moschitta_query/__init__.py
moschitta_query/expressions.py
moschitta_query/helpers.py
moschitta_query/query.py
moschitta_query-0.1.0.dist-info/LICENSE
moschitta_query-0.1.0.dist-info/METADATA
moschitta_query-0.1.0.dist-info/WHEEL
moschitta_query-0.1.0.dist-info/RECORD
