Metadata-Version: 2.1
Name: moschitta-query
Version: 0.1.0
Summary: Fluent Query Builder Library
Author: Skyler Saville
Author-email: skylersaville@gmail.com
Requires-Python: >=3.11,<4.0
Classifier: Programming Language :: Python :: 3
Classifier: Programming Language :: Python :: 3.11
